Workbook
Name Accessories: Products!$A$5
Name Electronics: Products!$A$2:$A$7
Name NativeTimeline_Date: #N/A
Name Office: Products!$A$7
Name Product_Categories: OFFSET(Products!$B$2, 0, 0, COUNTA(Products!$B:$B)-1, 1)
Name Slicer_Category: #N/A
Name Slicer_Customer_Classification: #N/A
Name Slicer_Date: #N/A
Name Slicer_Region: #N/A

Sheet Dashboard
A1: Dashboard
A2: Average Delivery Time | B2: =AVERAGE(Operations!B:B) -> 4.8888889 | I2: Row Labels | J2: Average of Delivery Days | K2: Average of Return Rate
A3: Average Return Rate | B3: =AVERAGE(Operations!C:C) -> 0.050555556 | I3: East | J3: 4.3809524 | K3: 0.055238095
A4: % of High Efficiency Orders | B4: =COUNTIFS(Operations!B:B, "<=5", Operations!C:C, "<=0,05") / COUNTA(Operations!A:A) -> 0.31868132 | I4: North | J4: 4.5909091 | K4: 0.046363636
I5: South | J5: 5.4347826 | K5: 0.053478261
A6: Total Revenue | B6: =PivotTables!H11 -> 441262 | I6: West | J6: 5.0833333 | K6: 0.0475
A7: Profit | B7: =PivotTables!I11 -> -726558 | I7: Grand Total | J7: 4.8888889 | K7: 0.050555556
A8: Top Customer | B8: =Sales_All!D8 -> 1017
A9: On-Time Delivery% | B9: =Sales_All!K94 -> 0.58888889
A12: Row Labels | B12: Sum of Revenue | C12: Sum of Profit
A13: East | B13: 104142 | C13: -187454
A14: North | B14: 87013 | C14: -20092
A15: South | B15: 124308 | C15: -529381
A16: West | B16: 125799 | C16: 10369
A17: Grand Total | B17: 441262 | C17: -726558

Sheet Sales_All
A1: OrderID | B1: Date | C1: Region | D1: CustomerID | E1: Product | F1: Quantity | G1: UnitPrice | H1: {=_xlfn.XLOOKUP(E1,Products!A:A,Products!B:E)} -> Category | I1: UnitPrice | J1: UnitCost | K1: Discount | L1: Gross Profit | M1: Delivery Days | N1: Return Rate | O1: Order Efficiency | P1: Revenue | Q1: Discounted Revenue | R1: Profit | S1: Customer Classification | T1: Product_Categories | U1: Region | V1: Order Count | W1: Avg Delivery Days | X1: Unique customer purchase
A2: Q1-001 | B2: 45708.027 | C2: South | D2: 1018 | E2: Tablet | F2: 1 | G2: 730 | H2: {=_xlfn.XLOOKUP(E2,Products!A:A,Products!B:E)} -> Electronics | I2: 1613 | J2: 492 | K2: 0.14 | L2: =(F2 * I2 * (1 - K2)) - (F2 * J2) -> 895.18 | M2: =_xlfn.XLOOKUP(A2, Operations!A:A, Operations!B:B) -> 5 | N2: =_xlfn.XLOOKUP(A2, Operations!A:A, Operations!C:C) -> 0.01 | O2: =IF(AND(M2<=5, N2<=0.05), "High Efficiency", "Low Efficiency") -> High Efficiency | P2: =F2*G2 -> 730 | Q2: =P2*(1-K2%) -> 728.978 | R2: =P2-(F2-J2)-(Finance!B2+Finance!C2+Finance!D2) -> -105993 | S2: {=_xlfn.IFS(Q2>50000, "VIP", Q2>=20000, "Regular", Q2<20000, "Low Value")} -> Low Value | T2: Headphones | U2: South | V2: =COUNTIF(C:C, "South") -> 23 | W2: =AVERAGEIF($C:$C, "South",$M:$M) -> 5.4347826 | X2: {=_xlfn.TEXTJOIN(", ", TRUE, _xlfn.UNIQUE(_xlfn._xlws.FILTER(Sales_All!$E$2:$E$91, Sales_All!$D$2:$D$91 = D2, "")))} -> Tablet, Smartphone, Headphones, Monitor, Laptop
A3: Q1-002 | B3: 45712.237 | C3: South | D3: 1004 | E3: Headphones | F3: 3 | G3: 378 | H3: {=_xlfn.XLOOKUP(E3,Products!A:A,Products!B:E)} -> Accessories | I3: 106 | J3: 323 | K3: 0.1 | L3: =(F3 * I3 * (1 - K3)) - (F3 * J3) -> -682.8 | M3: =_xlfn.XLOOKUP(A3, Operations!A:A, Operations!B:B) -> 2 | N3: =_xlfn.XLOOKUP(A3, Operations!A:A, Operations!C:C) -> 0.03 | O3: =IF(AND(M3<=5, N3<=0.05), "High Efficiency", "Low Efficiency") -> High Efficiency | P3: =F3*G3 -> 1134 | Q3: =P3*(1-K3%) -> 1132.866 | R3: =P3-(F3-J3)-(Finance!B3+Finance!C3+Finance!D3) -> -140123 | S3: {=_xlfn.IFS(Q3>50000, "VIP", Q3>=20000, "Regular", Q3<20000, "Low Value")} -> Low Value | T3: Headphones | U3: West | V3: =COUNTIF(C:C, "West") -> 24 | W3: =AVERAGEIF($C:$C, "West",$M:$M) -> 5.0833333 | X3: {=_xlfn.TEXTJOIN(", ", TRUE, _xlfn.UNIQUE(_xlfn._xlws.FILTER(Sales_All!$E$2:$E$91, Sales_All!$D$2:$D$91 = D3, "")))} -> Headphones, Printer, Laptop
A4: Q1-003 | B4: 45736.268 | C4: West | D4: 1005 | E4: Monitor | F4: 1 | G4: 585 | H4: {=_xlfn.XLOOKUP(E4,Products!A:A,Products!B:E)} -> Electronics | I4: 396 | J4: 463 | K4: 0.23 | L4: =(F4 * I4 * (1 - K4)) - (F4 * J4) -> -158.08 | M4: =_xlfn.XLOOKUP(A4, Operations!A:A, Operations!B:B) -> 6 | N4: =_xlfn.XLOOKUP(A4, Operations!A:A, Operations!C:C) -> 0.05 | O4: =IF(AND(M4<=5, N4<=0.05), "High Efficiency", "Low Efficiency") -> Low Efficiency | P4: =F4*G4 -> 585 | Q4: =P4*(1-K4%) -> 583.6545 | R4: =P4-(F4-J4)-(Finance!B4+Finance!C4+Finance!D4) -> -114728 | S4: {=_xlfn.IFS(Q4>50000, "VIP", Q4>=20000, "Regular", Q4<20000, "Low Value")} -> Low Value | T4: Monitor | U4: East | V4: =COUNTIF(C:C, "East") -> 21 | W4: =AVERAGEIF($C:$C, "East",$M:$M) -> 4.3809524 | X4: {=_xlfn.TEXTJOIN(", ", TRUE, _xlfn.UNIQUE(_xlfn._xlws.FILTER(Sales_All!$E$2:$E$91, Sales_All!$D$2:$D$91 = D4, "")))} -> Monitor, Printer, Tablet
A5: Q1-004 | B5: 45703.571 | C5: East | D5: 1018 | E5: Smartphone | F5: 8 | G5: 726 | H5: {=_xlfn.XLOOKUP(E5,Products!A:A,Products!B:E)} -> Electronics | I5: 1402 | J5: 97 | K5: 0.08 | L5: =(F5 * I5 * (1 - K5)) - (F5 * J5) -> 9542.72 | M5: =_xlfn.XLOOKUP(A5, Operations!A:A, Operations!B:B) -> 4 | N5: =_xlfn.XLOOKUP(A5, Operations!A:A, Operations!C:C) -> 0.07 | O5: =IF(AND(M5<=5, N5<=0.05), "High Efficiency", "Low Efficiency") -> Low Efficiency | P5: =F5*G5 -> 5808 | Q5: =P5*(1-K5%) -> 5803.3536 | R5: =P5-(F5-J5)-(Finance!B5+Finance!C5+Finance!D5) -> -150352 | S5: {=_xlfn.IFS(Q5>50000, "VIP", Q5>=20000, "Regular", Q5<20000, "Low Value")} -> Low Value | T5: Laptop | U5: North | V5: =COUNTIF(C:C, "North") -> 22 | W5: =AVERAGEIF($C:$C, "North",$M:$M) -> 4.5909091 | X5: {=_xlfn.TEXTJOIN(", ", TRUE, _xlfn.UNIQUE(_xlfn._xlws.FILTER(Sales_All!$E$2:$E$91, Sales_All!$D$2:$D$91 = D5, "")))} -> Tablet, Smartphone, Headphones, Monitor, Laptop
A6: Q1-005 | B6: 45663.686 | C6: North | D6: 1012 | E6: Laptop | F6: 2 | G6: 709 | H6: {=_xlfn.XLOOKUP(E6,Products!A:A,Products!B:E)} -> Electronics | I6: 1299 | J6: 469 | K6: 0.22 | L6: =(F6 * I6 * (1 - K6)) - (F6 * J6) -> 1088.44 | M6: =_xlfn.XLOOKUP(A6, Operations!A:A, Operations!B:B) -> 5 | N6: =_xlfn.XLOOKUP(A6, Operations!A:A, Operations!C:C) -> 0.03 | O6: =IF(AND(M6<=5, N6<=0.05), "High Efficiency", "Low Efficiency") -> High Efficiency | P6: =F6*G6 -> 1418 | Q6: =P6*(1-K6%) -> 1414.8804 | R6: =P6-(F6-J6)-(Finance!B6+Finance!C6+Finance!D6) -> -105603 | S6: {=_xlfn.IFS(Q6>50000, "VIP", Q6>=20000, "Regular", Q6<20000, "Low Value")} -> Low Value | X6: {=_xlfn.TEXTJOIN(", ", TRUE, _xlfn.UNIQUE(_xlfn._xlws.FILTER(Sales_All!$E$2:$E$91, Sales_All!$D$2:$D$91 = D6, "")))} -> Laptop, Headphones, Printer, Monitor
A7: Q1-006 | B7: 45716.227 | C7: East | D7: 1013 | E7: Laptop | F7: 8 | G7: 1817 | H7: {=_xlfn.XLOOKUP(E7,Products!A:A,Products!B:E)} -> Electronics | I7: 1299 | J7: 469 | K7: 0.22 | L7: =(F7 * I7 * (1 - K7)) - (F7 * J7) -> 4353.76 | M7: =_xlfn.XLOOKUP(A7, Operations!A:A, Operations!B:B) -> 5 | N7: =_xlfn.XLOOKUP(A7, Operations!A:A, Operations!C:C) -> 0.06 | O7: =IF(AND(M7<=5, N7<=0.05), "High Efficiency", "Low Efficiency") -> Low Efficiency | P7: =F7*G7 -> 14536 | Q7: =P7*(1-K7%) -> 14504.021 | R7: =P7-(F7-J7)-(Finance!B7+Finance!C7+Finance!D7) -> -120805 | S7: {=_xlfn.IFS(Q7>50000, "VIP", Q7>=20000, "Regular", Q7<20000, "Low Value")} -> Low Value | X7: {=_xlfn.TEXTJOIN(", ", TRUE, _xlfn.UNIQUE(_xlfn._xlws.FILTER(Sales_All!$E$2:$E$91, Sales_All!$D$2:$D$91 = D7, "")))} -> Laptop, Printer
A8: Q1-007 | B8: 45735.116 | C8: South | D8: 1017 | E8: Tablet | F8: 9 | G8: 1976 | M8: =_xlfn.XLOOKUP(A8, Operations!A:A, Operations!B:B) -> 4 | N8: =_xlfn.XLOOKUP(A8, Operations!A:A, Operations!C:C) -> 0.02 | O8: =IF(AND(M8<=5, N8<=0.05), "High Efficiency", "Low Efficiency") -> High Efficiency | P8: =F8*G8 -> 17784 | Q8: =P8*(1-K8%) -> 17784 | R8: =P8-(F8-J8)-(Finance!B8+Finance!C8+Finance!D8) -> -107279 | S8: {=_xlfn.IFS(Q8>50000, "VIP", Q8>=20000, "Regular", Q8<20000, "Low Value")} -> Low Value | X8: {=_xlfn.TEXTJOIN(", ", TRUE, _xlfn.UNIQUE(_xlfn._xlws.FILTER(Sales_All!$E$2:$E$91, Sales_All!$D$2:$D$91 = D8, "")))} -> Tablet, Laptop, Printer, Smartphone
A9: Q1-008 | B9: 45707.394 | C9: South | D9: 1014 | E9: Tablet | F9: 5 | G9: 1134 | M9: =_xlfn.XLOOKUP(A9, Operations!A:A, Operations!B:B) -> 8 | N9: =_xlfn.XLOOKUP(A9, Operations!A:A, Operations!C:C) -> 0.07 | O9: =IF(AND(M9<=5, N9<=0.05), "High Efficiency", "Low Efficiency") -> Low Efficiency | P9: =F9*G9 -> 5670 | Q9: =P9*(1-K9%) -> 5670 | R9: =P9-(F9-J9)-(Finance!B9+Finance!C9+Finance!D9) -> -141059 | S9: {=_xlfn.IFS(Q9>50000, "VIP", Q9>=20000, "Regular", Q9<20000, "Low Value")} -> Low Value | X9: {=_xlfn.TEXTJOIN(", ", TRUE, _xlfn.UNIQUE(_xlfn._xlws.FILTER(Sales_All!$E$2:$E$91, Sales_All!$D$2:$D$91 = D9, "")))} -> Tablet, Monitor, Headphones
A10: Q1-009 | B10: 45671.497 | C10: South | D10: 1020 | E10: Printer | F10: 1 | G10: 1220 | M10: =_xlfn.XLOOKUP(A10, Operations!A:A, Operations!B:B) -> 2 | N10: =_xlfn.XLOOKUP(A10, Operations!A:A, Operations!C:C) -> 0.08 | O10: =IF(AND(M10<=5, N10<=0.05), "High Efficiency", "Low Efficiency") -> Low Efficiency | P10: =F10*G10 -> 1220 | Q10: =P10*(1-K10%) -> 1220 | R10: =P10-(F10-J10)-(Finance!B10+Finance!C10+Finance!D10) -> -132619 | S10: {=_xlfn.IFS(Q10>50000, "VIP", Q10>=20000, "Regular", Q10<20000, "Low Value")} -> Low Value | X10: {=_xlfn.TEXTJOIN(", ", TRUE, _xlfn.UNIQUE(_xlfn._xlws.FILTER(Sales_All!$E$2:$E$91, Sales_All!$D$2:$D$91 = D10, "")))} -> Printer, Headphones, Laptop
A11: Q1-010 | B11: 45743.202 | C11: West | D11: 1010 | E11: Headphones | F11: 2 | G11: 283 | M11: =_xlfn.XLOOKUP(A11, Operations!A:A, Operations!B:B) -> 2 | N11: =_xlfn.XLOOKUP(A11, Operations!A:A, Operations!C:C) -> 0.08 | O11: =IF(AND(M11<=5, N11<=0.05), "High Efficiency", "Low Efficiency") -> Low Efficiency | P11: =F11*G11 -> 566 | Q11: =P11*(1-K11%) -> 566 | R11: =P11-(F11-J11)-(Finance!B11+Finance!C11+Finance!D11) -> 564 | S11: {=_xlfn.IFS(Q11>50000, "VIP", Q11>=20000, "Regular", Q11<20000, "Low Value")} -> Low Value | X11: {=_xlfn.TEXTJOIN(", ", TRUE, _xlfn.UNIQUE(_xlfn._xlws.FILTER(Sales_All!$E$2:$E$91, Sales_All!$D$2:$D$91 = D11, "")))} -> Headphones, Smartphone, Monitor, Printer
A12: Q1-011 | B12: 45684.929 | C12: West | D12: 1019 | E12: Laptop | F12: 9 | G12: 417 | M12: =_xlfn.XLOOKUP(A12, Operations!A:A, Operations!B:B) -> 8 | N12: =_xlfn.XLOOKUP(A12, Operations!A:A, Operations!C:C) -> 0.06 | O12: =IF(AND(M12<=5, N12<=0.05), "High Efficiency", "Low Efficiency") -> Low Efficiency | P12: =F12*G12 -> 3753 | Q12: =P12*(1-K12%) -> 3753 | R12: =P12-(F12-J12)-(Finance!B12+Finance!C12+Finance!D12) -> 3744 | S12: {=_xlfn.IFS(Q12>50000, "VIP", Q12>=20000, "Regular", Q12<20000, "Low Value")} -> Low Value | X12: {=_xlfn.TEXTJOIN(", ", TRUE, _xlfn.UNIQUE(_xlfn._xlws.FILTER(Sales_All!$E$2:$E$91, Sales_All!$D$2:$D$91 = D12, "")))} -> Laptop, Headphones, Tablet, Monitor
A13: Q1-012 | B13: 45662.79 | C13: South | D13: 1016 | E13: Laptop | F13: 3 | G13: 1692 | M13: =_xlfn.XLOOKUP(A13, Operations!A:A, Operations!B:B) -> 8 | N13: =_xlfn.XLOOKUP(A13, Operations!A:A, Operations!C:C) -> 0.03 | O13: =IF(AND(M13<=5, N13<=0.05), "High Efficiency", "Low Efficiency") -> Low Efficiency | P13: =F13*G13 -> 5076 | Q13: =P13*(1-K13%) -> 5076 | R13: =P13-(F13-J13)-(Finance!B13+Finance!C13+Finance!D13) -> 5073 | S13: {=_xlfn.IFS(Q13>50000, "VIP", Q13>=20000, "Regular", Q13<20000, "Low Value")} -> Low Value | X13: {=_xlfn.TEXTJOIN(", ", TRUE, _xlfn.UNIQUE(_xlfn._xlws.FILTER(Sales_All!$E$2:$E$91, Sales_All!$D$2:$D$91 = D13, "")))} -> Laptop, Monitor, Tablet
A14: Q1-013 | B14: 45693.46 | C14: East | D14: 1001 | E14: Printer | F14: 4 | G14: 1853 | M14: =_xlfn.XLOOKUP(A14, Operations!A:A, Operations!B:B) -> 1 | N14: =_xlfn.XLOOKUP(A14, Operations!A:A, Operations!C:C) -> 0.07 | O14: =IF(AND(M14<=5, N14<=0.05), "High Efficiency", "Low Efficiency") -> Low Efficiency | P14: =F14*G14 -> 7412 | Q14: =P14*(1-K14%) -> 7412 | R14: =P14-(F14-J14)-(Finance!B14+Finance!C14+Finance!D14) -> 7408 | S14: {=_xlfn.IFS(Q14>50000, "VIP", Q14>=20000, "Regular", Q14<20000, "Low Value")} -> Low Value | X14: {=_xlfn.TEXTJOIN(", ", TRUE, _xlfn.UNIQUE(_xlfn._xlws.FILTER(Sales_All!$E$2:$E$91, Sales_All!$D$2:$D$91 = D14, "")))} -> Printer, Monitor, Smartphone, Headphones, Laptop
A15: Q1-014 | B15: 45717.254 | C15: South | D15: 1005 | E15: Printer | F15: 2 | G15: 505 | M15: =_xlfn.XLOOKUP(A15, Operations!A:A, Operations!B:B) -> 3 | N15: =_xlfn.XLOOKUP(A15, Operations!A:A, Operations!C:C) -> 0.09 | O15: =IF(AND(M15<=5, N15<=0.05), "High Efficiency", "Low Efficiency") -> Low Efficiency | P15: =F15*G15 -> 1010 | Q15: =P15*(1-K15%) -> 1010 | R15: =P15-(F15-J15)-(Finance!B15+Finance!C15+Finance!D15) -> 1008 | S15: {=_xlfn.IFS(Q15>50000, "VIP", Q15>=20000, "Regular", Q15<20000, "Low Value")} -> Low Value | X15: {=_xlfn.TEXTJOIN(", ", TRUE, _xlfn.UNIQUE(_xlfn._xlws.FILTER(Sales_All!$E$2:$E$91, Sales_All!$D$2:$D$91 = D15, "")))} -> Monitor, Printer, Tablet
A16: Q1-015 | B16: 45672.073 | C16: South | D16: 1016 | E16: Monitor | F16: 3 | G16: 1355 | M16: =_xlfn.XLOOKUP(A16, Operations!A:A, Operations!B:B) -> 4 | N16: =_xlfn.XLOOKUP(A16, Operations!A:A, Operations!C:C) -> 0.06 | O16: =IF(AND(M16<=5, N16<=0.05), "High Efficiency", "Low Efficiency") -> Low Efficiency | P16: =F16*G16 -> 4065 | Q16: =P16*(1-K16%) -> 4065 | R16: =P16-(F16-J16)-(Finance!B16+Finance!C16+Finance!D16) -> 4062 | S16: {=_xlfn.IFS(Q16>50000, "VIP", Q16>=20000, "Regular", Q16<20000, "Low Value")} -> Low Value | X16: {=_xlfn.TEXTJOIN(", ", TRUE, _xlfn.UNIQUE(_xlfn._xlws.FILTER(Sales_All!$E$2:$E$91, Sales_All!$D$2:$D$91 = D16, "")))} -> Laptop, Monitor, Tablet
A17: Q1-016 | B17: 45742.873 | C17: North | D17: 1003 | E17: Printer | F17: 8 | G17: 1220 | M17: =_xlfn.XLOOKUP(A17, Operations!A:A, Operations!B:B) -> 3 | N17: =_xlfn.XLOOKUP(A17, Operations!A:A, Operations!C:C) -> 0.1 | O17: =IF(AND(M17<=5, N17<=0.05), "High Efficiency", "Low Efficiency") -> Low Efficiency | P17: =F17*G17 -> 9760 | Q17: =P17*(1-K17%) -> 9760 | R17: =P17-(F17-J17)-(Finance!B17+Finance!C17+Finance!D17) -> 9752 | S17: {=_xlfn.IFS(Q17>50000, "VIP", Q17>=20000, "Regular", Q17<20000, "Low Value")} -> Low Value | X17: {=_xlfn.TEXTJOIN(", ", TRUE, _xlfn.UNIQUE(_xlfn._xlws.FILTER(Sales_All!$E$2:$E$91, Sales_All!$D$2:$D$91 = D17, "")))} -> Printer, Monitor, Headphones
A18: Q1-017 | B18: 45688.214 | C18: North | D18: 1008 | E18: Smartphone | F18: 3 | G18: 605 | M18: =_xlfn.XLOOKUP(A18, Operations!A:A, Operations!B:B) -> 6 | N18: =_xlfn.XLOOKUP(A18, Operations!A:A, Operations!C:C) -> 0.1 | O18: =IF(AND(M18<=5, N18<=0.05), "High Efficiency", "Low Efficiency") -> Low Efficiency | P18: =F18*G18 -> 1815 | Q18: =P18*(1-K18%) -> 1815 | R18: =P18-(F18-J18)-(Finance!B18+Finance!C18+Finance!D18) -> 1812 | S18: {=_xlfn.IFS(Q18>50000, "VIP", Q18>=20000, "Regular", Q18<20000, "Low Value")} -> Low Value | X18: {=_xlfn.TEXTJOIN(", ", TRUE, _xlfn.UNIQUE(_xlfn._xlws.FILTER(Sales_All!$E$2:$E$91, Sales_All!$D$2:$D$91 = D18, "")))} -> Smartphone, Headphones, Laptop
A19: Q1-018 | B19: 45718.933 | C19: South | D19: 1009 | E19: Monitor | F19: 7 | G19: 1149 | M19: =_xlfn.XLOOKUP(A19, Operations!A:A, Operations!B:B) -> 9 | N19: =_xlfn.XLOOKUP(A19, Operations!A:A, Operations!C:C) -> 0.02 | O19: =IF(AND(M19<=5, N19<=0.05), "High Efficiency", "Low Efficiency") -> Low Efficiency | P19: =F19*G19 -> 8043 | Q19: =P19*(1-K19%) -> 8043 | R19: =P19-(F19-J19)-(Finance!B19+Finance!C19+Finance!D19) -> 8036 | S19: {=_xlfn.IFS(Q19>50000, "VIP", Q19>=20000, "Regular", Q19<20000, "Low Value")} -> Low Value | X19: {=_xlfn.TEXTJOIN(", ", TRUE, _xlfn.UNIQUE(_xlfn._xlws.FILTER(Sales_All!$E$2:$E$91, Sales_All!$D$2:$D$91 = D19, "")))} -> Monitor, Headphones, Smartphone, Laptop, Printer
... A91: Q3-030 | B91: 45898.259 | C91: West | D91: 1003 | E91: Monitor | F91: 3 | G91: 651 | M91: =_xlfn.XLOOKUP(A91, Operations!A:A, Operations!B:B) -> 5 | N91: =_xlfn.XLOOKUP(A91, Operations!A:A, Operations!C:C) -> 0.09 | O91: =IF(AND(M91<=5, N91<=0.05), "High Efficiency", "Low Efficiency") -> Low Efficiency | P91: =F91*G91 -> 1953 | Q91: =P91*(1-K91%) -> 1953 | R91: =P91-(F91-J91)-(Finance!B91+Finance!C91+Finance!D91) -> 1950 | S91: {=_xlfn.IFS(Q91>50000, "VIP", Q91>=20000, "Regular", Q91<20000, "Low Value")} -> Low Value | X91: {=_xlfn.TEXTJOIN(", ", TRUE, _xlfn.UNIQUE(_xlfn._xlws.FILTER(Sales_All!$E$2:$E$91, Sales_All!$D$2:$D$91 = D91, "")))} -> Printer, Monitor, Headphones
K93: On-Time Delivery%
K94: =COUNTIF(Sales_All!M2:M91, "<=5") / COUNTA(Sales_All!M2:M91) -> 0.58888889

Sheet Products
A1: Product | B1: Category | C1: UnitPrice | D1: UnitCost | E1: Discount
A2: Laptop | B2: Electronics | C2: 1299 | D2: 469 | E2: 0.22
A3: Tablet | B3: Electronics | C3: 1613 | D3: 492 | E3: 0.14
A4: Smartphone | B4: Electronics | C4: 1402 | D4: 97 | E4: 0.08
A5: Headphones | B5: Accessories | C5: 106 | D5: 323 | E5: 0.1
A6: Monitor | B6: Electronics | C6: 396 | D6: 463 | E6: 0.23
A7: Printer | B7: Office | C7: 1635 | D7: 136 | E7: 0.1

Sheet Customers
A1: CustomerID | B1: FirstName | C1: LastName | D1: Email | E1: Region | F1: Extracted First Name | G1: Extracted Last Name | H1: Extracted Email Domain
A2: 1001 | B2: Naledi | C2: Pillay | D2: naledi.pillay@example.com | E2: East | F2: =LEFT(D2, FIND(".", D2) - 1) -> naledi | G2: =MID(D2, FIND(".", D2) + 1, FIND("@", D2) - FIND(".", D2) - 1) -> pillay | H2: =RIGHT(D2, LEN(D2) - FIND("@", D2)) -> example.com
A3: 1002 | B3: Michael | C3: van Wyk | D3: michael.van wyk@example.com | E3: East | F3: =LEFT(D3, FIND(".", D3) - 1) -> michael | G3: =MID(D3, FIND(".", D3) + 1, FIND("@", D3) - FIND(".", D3) - 1) -> van wyk | H3: =RIGHT(D3, LEN(D3) - FIND("@", D3)) -> example.com
A4: 1003 | B4: Naledi | C4: Botha | D4: naledi.botha@example.com | E4: East | F4: =LEFT(D4, FIND(".", D4) - 1) -> naledi | G4: =MID(D4, FIND(".", D4) + 1, FIND("@", D4) - FIND(".", D4) - 1) -> botha | H4: =RIGHT(D4, LEN(D4) - FIND("@", D4)) -> example.com
A5: 1004 | B5: Naledi | C5: Botha | D5: naledi.botha@example.com | E5: North | F5: =LEFT(D5, FIND(".", D5) - 1) -> naledi | G5: =MID(D5, FIND(".", D5) + 1, FIND("@", D5) - FIND(".", D5) - 1) -> botha | H5: =RIGHT(D5, LEN(D5) - FIND("@", D5)) -> example.com
A6: 1005 | B6: Michael | C6: Johnson | D6: michael.johnson@example.com | E6: North | F6: =LEFT(D6, FIND(".", D6) - 1) -> michael | G6: =MID(D6, FIND(".", D6) + 1, FIND("@", D6) - FIND(".", D6) - 1) -> johnson | H6: =RIGHT(D6, LEN(D6) - FIND("@", D6)) -> example.com
A7: 1006 | B7: Emily | C7: Johnson | D7: emily.johnson@example.com | E7: South | F7: =LEFT(D7, FIND(".", D7) - 1) -> emily | G7: =MID(D7, FIND(".", D7) + 1, FIND("@", D7) - FIND(".", D7) - 1) -> johnson | H7: =RIGHT(D7, LEN(D7) - FIND("@", D7)) -> example.com
A8: 1007 | B8: Michael | C8: Nguyen | D8: michael.nguyen@example.com | E8: West | F8: =LEFT(D8, FIND(".", D8) - 1) -> michael | G8: =MID(D8, FIND(".", D8) + 1, FIND("@", D8) - FIND(".", D8) - 1) -> nguyen | H8: =RIGHT(D8, LEN(D8) - FIND("@", D8)) -> example.com
A9: 1008 | B9: Sipho | C9: Johnson | D9: sipho.johnson@example.com | E9: East | F9: =LEFT(D9, FIND(".", D9) - 1) -> sipho | G9: =MID(D9, FIND(".", D9) + 1, FIND("@", D9) - FIND(".", D9) - 1) -> johnson | H9: =RIGHT(D9, LEN(D9) - FIND("@", D9)) -> example.com
A10: 1009 | B10: Sarah | C10: Nguyen | D10: sarah.nguyen@example.com | E10: North | F10: =LEFT(D10, FIND(".", D10) - 1) -> sarah | G10: =MID(D10, FIND(".", D10) + 1, FIND("@", D10) - FIND(".", D10) - 1) -> nguyen | H10: =RIGHT(D10, LEN(D10) - FIND("@", D10)) -> example.com
A11: 1010 | B11: John | C11: Brown | D11: john.brown@example.com | E11: East | F11: =LEFT(D11, FIND(".", D11) - 1) -> john | G11: =MID(D11, FIND(".", D11) + 1, FIND("@", D11) - FIND(".", D11) - 1) -> brown | H11: =RIGHT(D11, LEN(D11) - FIND("@", D11)) -> example.com
A12: 1011 | B12: John | C12: Smith | D12: john.smith@example.com | E12: South | F12: =LEFT(D12, FIND(".", D12) - 1) -> john | G12: =MID(D12, FIND(".", D12) + 1, FIND("@", D12) - FIND(".", D12) - 1) -> smith | H12: =RIGHT(D12, LEN(D12) - FIND("@", D12)) -> example.com
A13: 1012 | B13: Naledi | C13: van Wyk | D13: naledi.van wyk@example.com | E13: East | F13: =LEFT(D13, FIND(".", D13) - 1) -> naledi | G13: =MID(D13, FIND(".", D13) + 1, FIND("@", D13) - FIND(".", D13) - 1) -> van wyk | H13: =RIGHT(D13, LEN(D13) - FIND("@", D13)) -> example.com
... A29: 1018 | B29: Michael | C29: Mlambo | D29: michael.mlambo@example.com | E29: South | F29: =LEFT(D29, FIND(".", D29) - 1) -> michael | G29: =MID(D29, FIND(".", D29) + 1, FIND("@", D29) - FIND(".", D29) - 1) -> mlambo | H29: =RIGHT(D29, LEN(D29) - FIND("@", D29)) -> example.com

Sheet Finance
A1: Month | B1: Overheads | C1: Salaries | D1: OtherExpenses | E1: Gross Profit | F1: Total Expenses | G1: Net Profit
A2: 45688 | B2: 25640 | C2: 60082 | D2: 21492 | E2: =SUMIFS(Sales_All!L:L, Sales_All!B:B, ">=" & EOMONTH(A2, -1)+1, Sales_All!B:B, "<=" & A2) -> 1088.44 | F2: =SUM(B2+C2+D2) -> 107214 | G2: =E2 - F2 -> -106125.56
A3: 45716 | B3: 43320 | C3: 70533 | D3: 27724 | E3: =SUMIFS(Sales_All!L:L, Sales_All!B:B, ">=" & EOMONTH(A3, -1)+1, Sales_All!B:B, "<=" & A3) -> 9755.1 | F3: =SUM(B3+C3+D3) -> 141577 | G3: =E3 - F3 -> -131821.9
A4: 45747 | B4: 34147 | C4: 63890 | D4: 17738 | E4: =SUMIFS(Sales_All!L:L, Sales_All!B:B, ">=" & EOMONTH(A4, -1)+1, Sales_All!B:B, "<=" & A4) -> -158.08 | F4: =SUM(B4+C4+D4) -> 115775 | G4: =E4 - F4 -> -115933.08
A5: 45777 | B5: 44423 | C5: 90674 | D5: 21152 | F5: =SUM(B5+C5+D5) -> 156249 | G5: =E5 - F5 -> -156249
A6: 45808 | B6: 32119 | C6: 55646 | D6: 19723 | F6: =SUM(B6+C6+D6) -> 107488 | G6: =E6 - F6 -> -107488
A7: 45838 | B7: 20079 | C7: 99954 | D7: 15769 | F7: =SUM(B7+C7+D7) -> 135802 | G7: =E7 - F7 -> -135802
A8: 45869 | B8: 36304 | C8: 63297 | D8: 25453 | F8: =SUM(B8+C8+D8) -> 125054 | G8: =E8 - F8 -> -125054
A9: 45900 | B9: 36734 | C9: 93760 | D9: 16230 | F9: =SUM(B9+C9+D9) -> 146724 | G9: =E9 - F9 -> -146724
A10: 45930 | B10: 34260 | C10: 70760 | D10: 28818 | F10: =SUM(B10+C10+D10) -> 133838 | G10: =E10 - F10 -> -133838

Sheet Operations
A1: OrderID | B1: DeliveryDays | C1: ReturnRate
A2: Q1-001 | B2: 5 | C2: 0.01
A3: Q1-002 | B3: 2 | C3: 0.03
A4: Q1-003 | B4: 6 | C4: 0.05
A5: Q1-004 | B5: 4 | C5: 0.07
A6: Q1-005 | B6: 5 | C6: 0.03
A7: Q1-006 | B7: 5 | C7: 0.06
A8: Q1-007 | B8: 4 | C8: 0.02
A9: Q1-008 | B9: 8 | C9: 0.07
A10: Q1-009 | B10: 2 | C10: 0.08
A11: Q1-010 | B11: 2 | C11: 0.08
A12: Q1-011 | B12: 8 | C12: 0.06
A13: Q1-012 | B13: 8 | C13: 0.03
... A91: Q3-030 | B91: 5 | C91: 0.09

Sheet PivotTables
A1: Pivot Tables
A3: Row Labels | B3: Sum of Revenue | C3: Sum of Profit | F3: Row Labels | G3: Sum of Profit | H3: Sum of Profit Margin %
A4: East | B4: 104142 | C4: -187454 | F4: Accessories | G4: -140123 | H4: -123.56526
A5: North | B5: 87013 | C5: -20092 | F5: Electronics | G5: -597481 | H5: -25.890757
A6: South | B6: 124308 | C6: -529381 | F6: Office | G6: 11046 | H6: 0.026485969
A7: West | B7: 125799 | C7: 10369 | F7: Grand Total | G7: -726558 | H7: -1.6465456
A8: Grand Total | B8: 441262 | C8: -726558
F9: Row Labels | G9: Count of CustomerID | H9: Sum of Revenue | I9: Sum of Profit
F10: Low Value | G10: 90 | H10: 441262 | I10: -726558
F11: Grand Total | G11: 90 | H11: 441262 | I11: -726558
F13: Row Labels | G13: Average of Delivery Days | H13: Average of Return Rate
F14: East | G14: 4.3809524 | H14: 0.055238095
F15: North | G15: 4.5909091 | H15: 0.046363636
F16: South | G16: 5.4347826 | H16: 0.053478261
F17: West | G17: 5.0833333 | H17: 0.0475
F18: Grand Total | G18: 4.8888889 | H18: 0.050555556
F20: Row Labels | G20: Sum of Revenue
F21: Headphones | G21: 92783
F22: Laptop | G22: 100036
F23: Monitor | G23: 100690
F24: Printer | G24: 49991
F25: Tablet | G25: 60019
F26: Grand Total | G26: 403519
